Metadata-Version: 1.0
Name: AxiomSDK
Version: 0.0
Summary: KLMG
Home-page: UNKNOWN
Author: UNKNOWN
Author-email: Pogrebnykh.Max@yandex.ru
License: UNKNOWN
Platform: UNKNOWN
